Metadata-Version: 2.1
Name: test-qt5-cef
Version: 1.1.8
Summary: A simple tool kit for create desktop application
Home-page: https://gitee.com/hycool/qt5_cef.git
Author: Burgeon Developer
Author-email: huai.y@burgeon.cn
License: UNKNOWN
Platform: UNKNOWN
Classifier: Programming Language :: Python :: 3
Classifier: License :: OSI Approved :: MIT License
Classifier: Operating System :: OS Independent
